text2tags/__init__.py
text2tags/tags.txt
text2tags_lib-0.0.7.dist-info/METADATA
text2tags_lib-0.0.7.dist-info/WHEEL
text2tags_lib-0.0.7.dist-info/top_level.txt
text2tags_lib-0.0.7.dist-info/RECORD
