Metadata-Version: 2.1
Name: text2tags-lib
Version: 0.0.7
Summary: Use a finetune of Llama-7b and llama cpp to predict Danbooru tags from natural text.
License: MIT License
Project-URL: Homepage, https://github.com/DatboiiPuntai/text2tags-lib
Project-URL: Download, https://github.com/DatboiiPuntai/text2tags-lib/archive/refs/heads/master.zip
Project-URL: Repository, https://github.com/DatboiiPuntai/text2tags-lib
Classifier: Development Status :: 4 - Beta
Classifier: License :: OSI Approved :: MIT License
Classifier: Programming Language :: Python
Requires-Dist: editdistance
Requires-Dist: llama-cpp-python ==0.2.27
Requires-Dist: wget
